limitless_tools/__init__.py
limitless_tools/_version.py
limitless_tools/errors.py
limitless_tools/py.typed
limitless_tools/cli/__init__.py
limitless_tools/cli/main.py
limitless_tools/config/__init__.py
limitless_tools/config/config.py
limitless_tools/config/env.py
limitless_tools/config/logging.py
limitless_tools/config/paths.py
limitless_tools/http/__init__.py
limitless_tools/http/client.py
limitless_tools/models/__init__.py
limitless_tools/models/lifelog.py
limitless_tools/services/__init__.py
limitless_tools/services/audio_service.py
limitless_tools/services/lifelog_service.py
limitless_tools/storage/__init__.py
limitless_tools/storage/json_repo.py
limitless_tools/storage/state_repo.py
limitless_tools-0.1.0.dist-info/licenses/LICENSE
limitless_tools-0.1.0.dist-info/METADATA
limitless_tools-0.1.0.dist-info/WHEEL
limitless_tools-0.1.0.dist-info/entry_points.txt
limitless_tools-0.1.0.dist-info/top_level.txt
limitless_tools-0.1.0.dist-info/RECORD
