Metadata-Version: 2.4
Name: limitless-tools
Version: 0.1.0
Summary: Library and CLI to fetch Limitless lifelogs and store locally
Author-email: Scott Kostolni <ScottKostolni@gmail.com>
License-Expression: MIT
Project-URL: Homepage, https://github.com/ScottSucksAtProgramming/limitless_tools
Project-URL: Issues, https://github.com/ScottSucksAtProgramming/limitless_tools/issues
Project-URL: Documentation, https://github.com/ScottSucksAtProgramming/limitless_tools#readme
Keywords: cli,limitless,lifelog,api,sync
Classifier: Development Status :: 3 - Alpha
Classifier: Programming Language :: Python :: 3 :: Only
Classifier: Programming Language :: Python :: 3.11
Classifier: Operating System :: OS Independent
Classifier: Intended Audience :: Developers
Classifier: Topic :: Software Development :: Libraries
Requires-Python: >=3.11
License-File: LICENSE
Requires-Dist: requests<3,>=2.31
Requires-Dist: pydantic<3,>=2.6
Requires-Dist: python-dotenv<2,>=1
Requires-Dist: tzlocal<6,>=5
Provides-Extra: dev
Requires-Dist: pytest<9,>=8; extra == "dev"
Requires-Dist: ruff>=0.6; extra == "dev"
Requires-Dist: mypy>=1.10; extra == "dev"
Requires-Dist: pip-audit<3,>=2.7; extra == "dev"
Requires-Dist: bandit<2,>=1.7; extra == "dev"
Requires-Dist: build<2,>=1; extra == "dev"
Requires-Dist: twine<7,>=5; extra == "dev"
Requires-Dist: pre-commit<4,>=3.7; extra == "dev"
Provides-Extra: test
Requires-Dist: pytest<9,>=8; extra == "test"
Dynamic: license-file
